retailcrm/__init__.py
retailcrm/response.py
retailcrm/versions/__init__.py
retailcrm/versions/base.py
retailcrm/versions/v3.py
retailcrm/versions/v4.py
retailcrm/versions/v5.py
retailcrm-5.3.0.dist-info/METADATA
retailcrm-5.3.0.dist-info/WHEEL
retailcrm-5.3.0.dist-info/licenses/LICENSE
retailcrm-5.3.0.dist-info/RECORD
