Metadata-Version: 2.4
Name: retailcrm
Version: 5.3.0
Summary: RetailCRM API client
Project-URL: Homepage, https://github.com/retailcrm/api-client-python
Project-URL: Issues, https://github.com/retailcrm/api-client-python/issues
Author-email: Alex Lushpai <lushpai@gmail.com>
Maintainer-email: Alex Lushpai <lushpai@gmail.com>
License-Expression: MIT
License-File: LICENSE
Keywords: api,ecom,retailcrm
Classifier: Development Status :: 5 - Production/Stable
Classifier: Environment :: Other Environment
Classifier: Intended Audience :: Developers
Classifier: Operating System :: OS Independent
Classifier: Programming Language :: Python
Classifier: Programming Language :: Python :: 3
Classifier: Programming Language :: Python :: 3 :: Only
Classifier: Programming Language :: Python :: 3.8
Classifier: Programming Language :: Python :: 3.9
Classifier: Programming Language :: Python :: 3.10
Classifier: Programming Language :: Python :: 3.11
Classifier: Programming Language :: Python :: 3.12
Classifier: Topic :: Software Development :: Libraries :: Python Modules
Requires-Python: >=3.8
Requires-Dist: multidimensional-urlencode==0.0.4
Requires-Dist: requests~=2.32.4
Provides-Extra: dev
Requires-Dist: coverage==4.5.4; extra == 'dev'
Requires-Dist: flake8; extra == 'dev'
Requires-Dist: nose==1.3.7; extra == 'dev'
Requires-Dist: pook==1.3.0; extra == 'dev'
